Vending_Machine/fifo_vending.sv
module fifo_vending #(
    parameter WIDTH = 1,
    parameter DEPTH = 8,
    parameter ADDR_WIDTH = 3
)(
    input  logic clk,
    input  logic rst,

    input  logic load_en,
    input  logic in,

    input  logic coke_in,
    input  logic pepsi_in,

    input  logic dispence_coke,
    input  logic dispence_pepsi,

    output logic out,

    output logic full_coke,
    output logic full_pepsi,

    output logic empty_coke,
    output logic empty_pepsi
);

////////////////////////////////////////////////////////////
// SHARED MEMORY
////////////////////////////////////////////////////////////

logic mem [0:DEPTH-1];

////////////////////////////////////////////////////////////
// POINTERS
////////////////////////////////////////////////////////////

// Coke uses addresses 0-3
logic [ADDR_WIDTH-1:0] coke_wr_ptr;
logic [ADDR_WIDTH-1:0] coke_rd_ptr;

// Pepsi uses addresses 4-7
logic [ADDR_WIDTH-1:0] pepsi_wr_ptr;
logic [ADDR_WIDTH-1:0] pepsi_rd_ptr;

////////////////////////////////////////////////////////////
// COUNTS
////////////////////////////////////////////////////////////

logic [2:0] coke_count;
logic [2:0] pepsi_count;

////////////////////////////////////////////////////////////
// STATUS FLAGS
////////////////////////////////////////////////////////////

assign full_coke   = (coke_count  == 4);
assign empty_coke  = (coke_count  == 0);

assign full_pepsi  = (pepsi_count == 4);
assign empty_pepsi = (pepsi_count == 0);

////////////////////////////////////////////////////////////
// MAIN LOGIC
////////////////////////////////////////////////////////////

always_ff @(posedge clk) begin

    ////////////////////////////////////////////////////////
    // RESET
    ////////////////////////////////////////////////////////

    if(rst) begin

        out <= 0;

        // Coke region -> 0 to 3
        coke_wr_ptr <= 0;
        coke_rd_ptr <= 0;

        // Pepsi region -> 4 to 7
        pepsi_wr_ptr <= 4;
        pepsi_rd_ptr <= 4;

        coke_count <= 0;
        pepsi_count <= 0;

    end

    ////////////////////////////////////////////////////////
    // NORMAL OPERATION
    ////////////////////////////////////////////////////////

    else begin

        ////////////////////////////////////////////////////
        // COKE WRITE
        ////////////////////////////////////////////////////

        if(coke_in && !full_coke) begin

            mem[coke_wr_ptr] <= in;

            coke_count <= coke_count + 1;

            // wrap inside 0-3
            if(coke_wr_ptr == 3)
                coke_wr_ptr <= 0;
            else
                coke_wr_ptr <= coke_wr_ptr + 1;

        end

        ////////////////////////////////////////////////////
        // PEPSI WRITE
        ////////////////////////////////////////////////////

        else if(pepsi_in && !full_pepsi) begin

            mem[pepsi_wr_ptr] <= in;

            pepsi_count <= pepsi_count + 1;

            // wrap inside 4-7
            if(pepsi_wr_ptr == 7)
                pepsi_wr_ptr <= 4;
            else
                pepsi_wr_ptr <= pepsi_wr_ptr + 1;

        end

        ////////////////////////////////////////////////////
        // COKE DISPENSE
        ////////////////////////////////////////////////////

        if(dispence_coke && !empty_coke) begin

            out <= mem[coke_rd_ptr];

            coke_count <= coke_count - 1;

            // wrap inside 0-3
            if(coke_rd_ptr == 3)
                coke_rd_ptr <= 0;
            else
                coke_rd_ptr <= coke_rd_ptr + 1;

        end

        ////////////////////////////////////////////////////
        // PEPSI DISPENSE
        ////////////////////////////////////////////////////

        else if(dispence_pepsi && !empty_pepsi) begin

            out <= mem[pepsi_rd_ptr];

            pepsi_count <= pepsi_count - 1;

            // wrap inside 4-7
            if(pepsi_rd_ptr == 7)
                pepsi_rd_ptr <= 4;
            else
                pepsi_rd_ptr <= pepsi_rd_ptr + 1;

        end

    end

end

endmodule

Vending_Machine/vending_design.sv
//Design of a simple Vending machine
module vending_machine (
    input logic clk,
    input logic rst,
    input logic coke, pepsi,
    input logic Cancel,load,
    input logic [3:0] amount,
    input logic dispence,
    output logic dispence_coke, dispence_pepsi, 
    output logic load_en,coke_in,pepsi_in
);

parameter IDLE = 3'b000, 
          SELECT   = 3'b001, 
          WAIT_MONEY   = 3'b010,
          LOAD  =    3'b011,
          PRODUCT = 3'b100;
        //   END = 3'b101;



logic [2:0] state, next_state;
logic select_coke, select_pepsi;

// State transition logic
always_ff @(posedge clk) begin
    if (rst || Cancel) begin
        state <= IDLE;
        
    end else begin
        state <= next_state;
    end
end

always_ff @(posedge clk ) begin 
      if(rst) begin
        select_coke  <= 0;
        select_pepsi <= 0;
        
    end else if(coke)begin
        select_coke <= 1;
        select_pepsi <= 0;
    end else if(pepsi)begin
        select_pepsi <= 1;
        select_coke <= 0;
    end else if(state == PRODUCT) begin
        select_coke <= 0;
        select_pepsi <= 0;
    end
end

// Next state logic
always_comb begin


dispence_coke = 0;
dispence_pepsi = 0;
next_state = state;
load_en = 0;
coke_in = 0;
pepsi_in = 0;



    case(state)
    IDLE:begin
        if(coke || pepsi)begin
            next_state = SELECT;
        end else begin
            next_state = IDLE;
        end
    end

    SELECT:begin
        if(load)begin
            load_en = 1;
            next_state = LOAD;

        end else if(dispence)begin
            next_state = WAIT_MONEY;
        end else begin
            next_state = SELECT;
        end
    end

    LOAD:begin
        if(select_coke)begin
            coke_in = 1;
            next_state = IDLE;
        end else if(select_pepsi)begin
            pepsi_in = 1;
            next_state = IDLE;
        end else begin
            next_state = IDLE;        
        end
    end

    WAIT_MONEY:begin
        if(amount > 10)begin
            next_state = PRODUCT;
        end else if(Cancel)begin
            next_state = IDLE;
        end else begin
            next_state = WAIT_MONEY;
        end
    end

    PRODUCT:begin
        if(select_coke)begin
            dispence_coke = 1;
        end else if(select_pepsi)begin
            dispence_pepsi = 1;
        end
        next_state = IDLE;
    end

    default: next_state = IDLE;
    endcase
end

endmodule

Vending_Machine/vending_top.sv
module top(
    input logic clk,
    input logic rst,
    input logic coke,
    input logic pepsi,
    input logic Cancel,
    input logic load,
    input logic [3:0] amount,
    input logic dispence
);

logic dispence_coke, dispence_pepsi;
logic load_en, coke_in, pepsi_in;

logic out;

logic full_coke, full_pepsi;
logic empty_coke, empty_pepsi;

logic in_data;

assign in_data = coke_in ? 1'b1 : pepsi_in ? 1'b0 : 1'b0;

//////////////////////////////////////////////////////////
// VENDING MACHINE
//////////////////////////////////////////////////////////

vending_machine vm (
    .clk(clk),
    .rst(rst),
    .coke(coke),
    .pepsi(pepsi),
    .Cancel(Cancel),
    .load(load),
    .amount(amount),
    .dispence(dispence),
    .dispence_coke(dispence_coke),
    .dispence_pepsi(dispence_pepsi),
    .load_en(load_en),
    .coke_in(coke_in),
    .pepsi_in(pepsi_in)
);

//////////////////////////////////////////////////////////
// FIFO
//////////////////////////////////////////////////////////

fifo_vending fifo (
    .clk(clk),
    .rst(rst),
    .load_en(load_en),
    .in(in_data),
    .coke_in(coke_in),
    .pepsi_in(pepsi_in),
    .dispence_coke(dispence_coke),
    .dispence_pepsi(dispence_pepsi),
    .out(out),
    .full_coke(full_coke),
    .full_pepsi(full_pepsi),
    .empty_coke(empty_coke),
    .empty_pepsi(empty_pepsi)
);

endmodule

Vending_Machine/vending_testbench.sv
module tb_top;

    logic clk;
    logic rst;

    logic coke;
    logic pepsi;

    logic Cancel;
    logic load;

    logic [3:0] amount;

    logic dispence;

    //////////////////////////////////////////////////////////
    // DUT
    //////////////////////////////////////////////////////////

    top dut(
        .clk(clk),
        .rst(rst),
        .coke(coke),
        .pepsi(pepsi),
        .Cancel(Cancel),
        .load(load),
        .amount(amount),
        .dispence(dispence)
    );

    //////////////////////////////////////////////////////////
    // CLOCK
    //////////////////////////////////////////////////////////

    initial begin
        clk = 0;
        forever #5 clk = ~clk;
    end

    //////////////////////////////////////////////////////////
    // STIMULUS
    //////////////////////////////////////////////////////////

    initial begin

        //////////////////////////////////////////////////////
        // INITIAL VALUES
        //////////////////////////////////////////////////////

        rst      = 1;
        coke     = 0;
        pepsi    = 0;
        Cancel   = 0;
        load     = 0;
        amount   = 0;
        dispence = 0;

        //////////////////////////////////////////////////////
        // RESET
        //////////////////////////////////////////////////////

        #20;
        rst = 0;

        //////////////////////////////////////////////////////
        // LOAD COKE INTO FIFO
        //////////////////////////////////////////////////////

        @(posedge clk);
        coke = 1;

        @(posedge clk);
        load = 1;

        @(posedge clk);
        coke = 0;
        load = 0;

        //////////////////////////////////////////////////////
        // LOAD PEPSI INTO FIFO
        //////////////////////////////////////////////////////

        @(posedge clk);
        pepsi = 1;

        @(posedge clk);
        load = 1;

        @(posedge clk);
        pepsi = 0;
        load = 0;

        //////////////////////////////////////////////////////
        // BUY COKE
        //////////////////////////////////////////////////////

        @(posedge clk);
        coke = 1;

        @(posedge clk);
        dispence = 1;

        @(posedge clk);
        amount = 12;

        @(posedge clk);
        coke = 0;
        dispence = 0;
        amount = 0;

        //////////////////////////////////////////////////////
        // BUY PEPSI
        //////////////////////////////////////////////////////

        @(posedge clk);
        pepsi = 1;

        @(posedge clk);
        dispence = 1;

        @(posedge clk);
        amount = 13;

        @(posedge clk);
        pepsi = 0;
        dispence = 0;
        amount = 0;

        //////////////////////////////////////////////////////
        // CANCEL TEST
        //////////////////////////////////////////////////////

        @(posedge clk);
        coke = 1;

        @(posedge clk);
        Cancel = 1;

        @(posedge clk);
        Cancel = 0;
        coke = 0;

        //////////////////////////////////////////////////////
        // END SIMULATION
        //////////////////////////////////////////////////////

        #50;
        $finish;

    end

    //////////////////////////////////////////////////////////
    // DUMP WAVES
    //////////////////////////////////////////////////////////

    initial begin
        $dumpfile("wave.vcd");
        $dumpvars(0, tb_top);
    end

endmodule

Vending_Machine/wave.vcd
$date
	Tue May 26 04:41:30 2026
$end
$version
	Icarus Verilog
$end
$timescale
	1s
$end
$scope module tb_top $end
$var reg 1 ! Cancel $end
$var reg 4 " amount [3:0] $end
$var reg 1 # clk $end
$var reg 1 $ coke $end
$var reg 1 % dispence $end
$var reg 1 & load $end
$var reg 1 ' pepsi $end
$var reg 1 ( rst $end
$scope module dut $end
$var wire 1 ! Cancel $end
$var wire 4 ) amount [3:0] $end
$var wire 1 # clk $end
$var wire 1 $ coke $end
$var wire 1 % dispence $end
$var wire 1 & load $end
$var wire 1 ' pepsi $end
$var wire 1 ( rst $end
$var wire 1 * pepsi_in $end
$var wire 1 + out $end
$var wire 1 , load_en $end
$var wire 1 - in_data $end
$var wire 1 . full_pepsi $end
$var wire 1 / full_coke $end
$var wire 1 0 empty_pepsi $end
$var wire 1 1 empty_coke $end
$var wire 1 2 dispence_pepsi $end
$var wire 1 3 dispence_coke $end
$var wire 1 4 coke_in $end
$scope module fifo $end
$var wire 1 # clk $end
$var wire 1 - in $end
$var wire 1 ( rst $end
$var wire 1 * pepsi_in $end
$var wire 1 , load_en $end
$var wire 1 . full_pepsi $end
$var wire 1 / full_coke $end
$var wire 1 0 empty_pepsi $end
$var wire 1 1 empty_coke $end
$var wire 1 2 dispence_pepsi $end
$var wire 1 3 dispence_coke $end
$var wire 1 4 coke_in $end
$var parameter 32 5 ADDR_WIDTH $end
$var parameter 32 6 DEPTH $end
$var parameter 32 7 WIDTH $end
$var reg 3 8 coke_count [2:0] $end
$var reg 3 9 coke_rd_ptr [2:0] $end
$var reg 3 : coke_wr_ptr [2:0] $end
$var reg 1 + out $end
$var reg 3 ; pepsi_count [2:0] $end
$var reg 3 < pepsi_rd_ptr [2:0] $end
$var reg 3 = pepsi_wr_ptr [2:0] $end
$upscope $end
$scope module vm $end
$var wire 1 ! Cancel $end
$var wire 4 > amount [3:0] $end
$var wire 1 # clk $end
$var wire 1 $ coke $end
$var wire 1 % dispence $end
$var wire 1 & load $end
$var wire 1 ' pepsi $end
$var wire 1 ( rst $end
$var parameter 3 ? IDLE $end
$var parameter 3 @ LOAD $end
$var parameter 3 A PRODUCT $end
$var parameter 3 B SELECT $end
$var parameter 3 C WAIT_MONEY $end
$var reg 1 4 coke_in $end
$var reg 1 3 dispence_coke $end
$var reg 1 2 dispence_pepsi $end
$var reg 1 , load_en $end
$var reg 3 D next_state [2:0] $end
$var reg 1 * pepsi_in $end
$var reg 1 E select_coke $end
$var reg 1 F select_pepsi $end
$var reg 3 G state [2:0] $end
$upscope $end
$upscope $end
$upscope $end
$enddefinitions $end
$comment Show the parameter values. $end
$dumpall
b10 C
b1 B
b100 A
b11 @
b0 ?
b1 7
b1000 6
b11 5
$end
#0
$dumpvars
bx G
xF
xE
b0 D
b0 >
bx =
bx <
bx ;
bx :
bx 9
bx 8
04
03
02
x1
x0
x/
x.
0-
0,
x+
0*
b0 )
1(
0'
0&
0%
0$
0#
b0 "
0!
$end
#5
b0 G
0F
0E
0.
10
b0 ;
0/
11
b0 8
b100 <
b100 =
b0 9
b0 :
0+
1#
#10
0#
#15
1#
#20
0#
0(
#25
1E
b1 D
1$
1#
#30
0#
#35
1,
b1 G
b11 D
1&
1#
#40
0#
#45
1-
14
b11 G
0,
b0 D
0&
0$
1#
#50
0#
#55
0-
b1 :
01
b1 8
b0 G
04
b1 D
1'
1#
#60
0#
#65
1,
b1 G
0E
1F
b11 D
1&
1#
#70
0#
#75
1*
b11 G
0,
b0 D
0&
0'
1#
#80
0#
#85
b0 G
0F
1E
b101 =
00
b1 ;
0*
b1 D
1$
1#
#90
0#
#95
b1 G
b10 D
1%
1#
#100
0#
#105
b10 G
b100 D
b1100 "
b1100 )
b1100 >
1#
#110
0#
#115
13
b100 G
b0 D
b0 "
b0 )
b0 >
0%
0$
1#
#120
0#
#125
b0 G
0E
1F
b1 9
11
b0 8
1+
b1 D
03
1'
1#
#130
0#
#135
b1 G
b10 D
1%
1#
#140
0#
#145
b10 G
b100 D
b1101 "
b1101 )
b1101 >
1#
#150
0#
#155
12
b100 G
b0 D
b0 "
b0 )
b0 >
0%
0'
1#
#160
0#
#165
b0 G
0F
1E
b101 <
10
b0 ;
0+
b1 D
02
1$
1#
#170
0#
#175
b1 G
b1 D
1!
1#
#180
0#
#185
0$
0!
1#
