Verification/FIFO/fifo_design.sv
// Synchronous FIFO
// Operations-> Write, Read, Full_flag, Empty_flag, Count
// Parameterized depth and widths


module sync_fifo #(
    parameter DATA_WIDTH = 8, 
    parameter DEPTH = 16)
    (
        input wire       clk,
        input wire       rst,

        input wire       wr_en,
        input wire       rd_en,

        input wire [DATA_WIDTH-1:0] din,
        output reg [DATA_WIDTH-1:0] dout,

        output wire       full,
        output wire       empty
    );

    localparam ADDR_WIDTH = $clog2(DEPTH);

    // Memory array
    reg [DATA_WIDTH-1:0] mem [0:DEPTH-1];

    // pointers
    reg [ADDR_WIDTH-1:0] wr_ptr;
    reg [ADDR_WIDTH-1:0] rd_ptr;

    // counter to count the number of writes 
    reg [ADDR_WIDTH:0] count;



    // write logic
    always @(posedge clk) begin
        if(rst) begin
            wr_ptr <= 0;
        end
        else if (wr_en && !full) begin     // First error - 1 (Error File)
            mem[wr_ptr] <= din;
            wr_ptr <= wr_ptr + 1;
        end
    end



    // Read logic
    always @(posedge clk) begin
        if(rst) begin
            rd_ptr  <= 0;
            dout    <= 0;
        end
        else if(rd_en && !empty) begin  // First error - 1 (Error File)
            dout <= mem[rd_ptr];
            rd_ptr <= rd_ptr + 1;
        end
    end


    // counter logic
    always @(posedge clk) begin
        if(rst) begin
            count <= 0;
        end
        else begin
            case ({wr_en && !full, rd_en && !empty})
                2'b10: count <= count + 1; // write only
                2'b01: count <= count - 1; // read only
                2'b11: count <= count ; // simultaneous read/write
                default: count <= count;
            endcase
        end
    end

    // status flags
    assign full = (count == DEPTH);

    assign empty = (count == 0);

endmodule

Verification/FIFO/fifo_testbench.sv
module fifo_test;
    parameter DEPTH = 16;
    reg clk;
    reg rst;
    reg wr_en;
    reg rd_en;
    reg [7:0] din;
    wire [7:0] dout;
    wire full;
    wire empty;

    sync_fifo #(
        .DATA_WIDTH(8),
        .DEPTH(DEPTH)
    ) fifo_inst (
        .clk(clk),
        .rst(rst),
        .wr_en(wr_en),
        .rd_en(rd_en),
        .din(din),
        .dout(dout),
        .full(full),
        .empty(empty)
    );

    ///////////////Properties and Assertions////////////////////

    property no_write_when_full;
        @(posedge clk) 
        // full &&  wr_en |-> $stable(fifo_inst.wr_ptr);
        full &&  wr_en |=> $stable(fifo_inst.wr_ptr);
    endproperty

    assert_no_write_when_full: assert property (no_write_when_full) else $error("Write occurred when FIFO was full!");  

    property no_read_when_empty;
        @(posedge clk) 
        // empty & rd_en |-> $stable(fifo_inst.rd_ptr);
        empty & rd_en |=> $stable(fifo_inst.rd_ptr);
    endproperty

    assert_no_read_when_empty: assert property (no_read_when_empty) else $error("Read occurred when FIFO was empty!"); 


    ///////////////Coverage////////////////////
   
    cover_full:
    cover property (@(posedge clk) full)
    $display("FIFO became FULL at time=%0t", $time);

    cover_empty:
    cover property (@(posedge clk) empty)
    $display("FIFO became EMPTY at time=%0t", $time);

    // cover_simultaneous_rw:
    // cover property (@(posedge clk) wr_en && rd_en)
    // $display("Simultaneous Read and Write at time=%0t", $time);

    cover_wrap:
    cover property (@(posedge clk)(fifo_inst.wr_ptr == 0) && ($past(fifo_inst.wr_ptr) == DEPTH-1))
    $display("WRITE POINTER WRAPPED");
    

    /////////////Classes and Randomization////////////////////
    class fifo_item;
    rand bit wr_en;
    rand bit rd_en;
    rand bit [7:0] din;

    constraint c1 {
        !(wr_en && rd_en); // Avoid conflicting read and write operations
    }
endclass


    class generator;

        fifo_item item;

        task run();
            item = new();
            repeat (20) begin
                item.randomize();

                wr_en <= item.wr_en;
                #20;
                rd_en <= item.rd_en;
                din <= item.din;
                #10;
            end
        endtask
    endclass

    initial begin
        $dumpfile("wave.vcd");
        $dumpvars(0, fifo_test);
    end

    // Clock generation
    initial begin
        clk = 0;
        forever #5 clk = ~clk; // 100MHz clock
    end

    // Test sequence
    initial begin
        // Initialize signals
        rst = 1;
        wr_en = 0;
        rd_en = 0;
        din = 0;

        // Reset the FIFO
        #10 rst = 0;
    end
    generator gen;

    initial begin
        gen = new();

        if (!gen.randomize())
            $error("randomization failed");
        gen.run();
        #50 $finish;

end

endmodule

Verification/FIFO/wave.vcd
$date
	Wed May 27 14:27:39 2026
$end
$version
	QuestaSim Version 10.7c
$end
$timescale
	1ns
$end

$scope module fifo_test $end

$scope begin assert_no_write_when_full $end
$upscope $end

$scope begin assert_no_read_when_empty $end
$upscope $end

$scope begin cover_full $end
$upscope $end

$scope begin cover_empty $end
$upscope $end

$scope begin cover_wrap $end
$upscope $end

$scope module fifo_inst $end
$var reg 4 ! wr_ptr [3:0] $end
$var reg 4 " rd_ptr [3:0] $end
$upscope $end
$upscope $end
$enddefinitions $end
#0
$dumpvars
bx !
bx "
$end
#5
b0 !
b0 "
#15
b1 !
#25
b10 !
#35
b1 "
#45
b10 "
#55
b11 !
#85
b100 !
#95
b11 "
#105
b101 !
#115
b110 !
#125
b100 "
#135
b101 "
#145
b110 "
#195
b111 !
#205
b1000 !
#215
b1001 !
#225
b1010 !
#235
b1011 !
#245
b1100 !
