PWM/pwm_design.sv
module pwm_design#(
    parameter duty = 4,
    parameter period = 8
)(
    input logic clk,
    input logic rst,
    output logic pwm_out
);

localparam int counter_width = $clog2(period);

logic [counter_width-1:0] counter;

always_ff @(posedge clk or posedge rst) begin
    if (rst) begin
        counter <= 0;
        pwm_out <= 0;
    end else begin
        if (counter < duty) begin
            pwm_out <= 1;
        end else begin
            pwm_out <= 0;
        end

        if (counter == period-1) begin
            counter <= 0;
        end else begin
            counter <= counter + 1;
        end
    end
end
endmodule

PWM/pwm_testbench.sv
module test;
    logic clk;
    logic rst;
    logic pwm_out;

    pwm_design #(
        .duty(4),
        .period(8)
    ) dut (
        .clk(clk),
        .rst(rst),
        .pwm_out(pwm_out)
    );

    initial begin
        clk = 0;
        rst = 1;
        #10 rst = 0; // Release reset after 10 time units
    end

    always #5 clk = ~clk; // Generate a clock with a period of 10 time units

    initial begin
        $dumpfile("wave.vcd");
        $dumpvars(0, test);
    end

    initial begin
        $monitor("Time: %0t | PWM Output: %b", $time, pwm_out);
        #100 $finish; // Run the simulation for 100 time units
    end

endmodule

PWM/wave.vcd
$date
	Tue May 26 11:29:18 2026
$end
$version
	Icarus Verilog
$end
$timescale
	1s
$end
$scope module test $end
$var wire 1 ! pwm_out $end
$var reg 1 " clk $end
$var reg 1 # rst $end
$scope module dut $end
$var wire 1 " clk $end
$var wire 1 # rst $end
$var parameter 32 $ counter_width $end
$var parameter 32 % duty $end
$var parameter 32 & period $end
$var reg 3 ' counter [2:0] $end
$var reg 1 ! pwm_out $end
$upscope $end
$upscope $end
$enddefinitions $end
$comment Show the parameter values. $end
$dumpall
b1000 &
b100 %
b11 $
$end
#0
$dumpvars
b0 '
1#
0"
0!
$end
#5
1"
#10
0"
0#
#15
b1 '
1!
1"
#20
0"
#25
b10 '
1"
#30
0"
#35
b11 '
1"
#40
0"
#45
b100 '
1"
#50
0"
#55
b101 '
0!
1"
#60
0"
#65
b110 '
1"
#70
0"
#75
b111 '
1"
#80
0"
#85
b0 '
1"
#90
0"
#95
b1 '
1!
1"
