CDC/decoder_design.sv
module decoder_parameter#(
    parameter Width = 8
    )(
        input logic clk,
        input logic rst,
        input logic empty,
        input logic [Width-1:0] din,
        input logic full,
        output logic rd_en,
        output logic [Width-1:0]dout
);
// logic [3:0] counter;
logic [Width-1:0] pattern = 8'hA5; // Example pattern to decode
logic start_read, rd_valid;

always_ff@(posedge clk)  begin
    if (rst) begin
        start_read <= 0;
        dout <= 0;
        rd_en <= 0;
    end 

    else begin
        if (full)
        start_read <= 1;
        
        if (start_read && !empty ) begin
    
        rd_en <= 1; // Enable read when not empty
        // dout <= din ^ pattern; // Output the pattern
        // rd_valid <= 1; // Indicate that read data is valid

        // if(rd_valid) begin
            dout <= din ^ pattern; // Output the pattern
            // $display("[%0t] Decoded data = %0d", $time, dout);
        // end
        

    end 
     else begin
        rd_en <= 0; // Disable read when empty
    end
    end
end

endmodule

CDC/fifo_design.sv
module fifo_parameter#(
    parameter Width = 8,
    parameter Depth = 8
    )(
        input logic clk,
        input logic rst,
        input logic wr_en,
        input logic rd_en,
        input logic [Width-1:0]din,
        output logic [Width-1:0]dout,
        output logic full,empty
    );

    localparam Addr_Width =$clog2(Depth);

    reg [Width-1:0]mem[0:Depth-1];

    reg [Addr_Width:0]wr_ptr, rd_ptr;
    integer i;

    always_ff @(posedge clk)begin
        if(rst)begin
            wr_ptr <= 0;
            // mem <= '{default:0}; // not req
            for(i=0; i<Depth; i=i+1)begin
                mem[i] <= 0;
            end

        end

        else if(wr_en && !full)begin
            mem[wr_ptr[Addr_Width-1:0]] <= din;
            if(wr_ptr[Addr_Width-1:0] == Depth-1)begin
                wr_ptr <= {~wr_ptr[3], 3'b000}; // toggle MSB and reset LSBs
            end else begin
                wr_ptr <= wr_ptr + 1;
            end
        end
    end

    always_ff @(posedge clk)begin
        if(rst)begin
            rd_ptr <= 0;
            dout <= 0;
        end
        else if(rd_en && !empty)begin
            dout <= mem[rd_ptr[Addr_Width-1:0]];
            if(rd_ptr[Addr_Width-1:0] == Depth-1)begin
                rd_ptr <= {~rd_ptr[3], 3'b000}; // toggle MSB and reset LSBs
            end else begin
                rd_ptr <= rd_ptr + 1;
            end
        end
    end

    assign empty = (rd_ptr == wr_ptr);

    assign full = (wr_ptr[Addr_Width] != rd_ptr[Addr_Width] && wr_ptr[Addr_Width-1:0] == rd_ptr[Addr_Width-1:0]);
endmodule

CDC/encoder_design.sv
module encoder_parameter#(
    parameter Width = 8
    )(
        input logic clk,
        input logic rst,
        input logic full,
        output logic wr_en,
        output logic [Width-1:0]din
);
logic [Width-1:0] counter; 
logic [Width-1:0] pattern = 8'hA5; // Example pattern to encode

always_ff @(posedge clk) begin
    if (rst) begin
        counter <= 0;
        din <= 0;
        wr_en <= 0;
    end else if (!full) begin
        din <= pattern ^ counter; // Output the pattern
        wr_en <= 1; // Enable write when not full
        counter <= counter + 1; // Increment counter for next pattern (if needed)
    end else begin
        wr_en <= 0; // Disable write when full
    end
end
endmodule

CDC/enco_deco_top.sv
module top(

input logic clk_encoder,clk_decoder,
input logic rst
);
parameter Width = 8;
wire wr_en_top;
wire rd_en_top;
wire [Width-1:0]din_top;
wire [Width-1:0]dout_top;
wire full_top,empty_top;
wire [Width-1:0]dout;

//`include"functions.sv"

encoder_parameter #(Width) encoder(
    .clk(clk_encoder),
    .rst(rst),
    .full(full_top),
    .wr_en(wr_en_top),
    .din(din_top)
);
fifo_parameter #(Width,8) fifo(    // Depth instanciated 45 for CDC handling
    .clk(clk_encoder),
    .rst(rst),
    .wr_en(wr_en_top),
    .rd_en(rd_en_top),
    .din(din_top),
    .dout(dout_top),
    .full(full_top),
    .empty(empty_top)
);
decoder_parameter #(Width) decoder(
    .clk(clk_decoder),
    .rst(rst),
    .empty(empty_top),
    .rd_en(rd_en_top),
    .full(full_top),
    .din(dout_top),
    .dout(dout)
);

endmodule

CDC/testbench_enco_deco.sv
module test_bench_encoder;

reg rst;
reg clk_encoder;
reg clk_decoder;



top uut(
    
    .rst(rst),
    .clk_encoder(clk_encoder),
    .clk_decoder(clk_decoder)
);

// initial begin
//     clk = 0;
//     forever #5 clk = ~clk;
// end

initial begin
    clk_encoder = 0;
    forever #6.25 clk_encoder = ~clk_encoder;
end

initial begin
    clk_decoder = 0;
    forever #10 clk_decoder = ~clk_decoder;
end

initial begin
    rst = 1;
    #20;
    rst = 0;

    #200;   // let system run

    $finish;
end

initial begin
    $dumpfile("wave.vcd");
    $dumpvars(0, test_bench_encoder);
end

endmodule

CDC/wave.vcd
$date
	Thu May 21 11:17:24 2026
$end
$version
	Icarus Verilog
$end
$timescale
	1s
$end
$scope module test_bench_encoder $end
$var reg 1 ! clk_decoder $end
$var reg 1 " clk_encoder $end
$var reg 1 # rst $end
$scope module uut $end
$var wire 1 ! clk_decoder $end
$var wire 1 " clk_encoder $end
$var wire 1 # rst $end
$var wire 1 $ wr_en_top $end
$var wire 1 % rd_en_top $end
$var wire 1 & full_top $end
$var wire 1 ' empty_top $end
$var wire 8 ( dout_top [7:0] $end
$var wire 8 ) dout [7:0] $end
$var wire 8 * din_top [7:0] $end
$var parameter 32 + Width $end
$scope module decoder $end
$var wire 1 ! clk $end
$var wire 1 # rst $end
$var wire 1 & full $end
$var wire 1 ' empty $end
$var wire 8 , din [7:0] $end
$var parameter 32 - Width $end
$var reg 8 . dout [7:0] $end
$var reg 8 / pattern [7:0] $end
$var reg 1 % rd_en $end
$var reg 1 0 start_read $end
$upscope $end
$scope module encoder $end
$var wire 1 " clk $end
$var wire 1 # rst $end
$var wire 1 & full $end
$var parameter 32 1 Width $end
$var reg 8 2 counter [7:0] $end
$var reg 8 3 din [7:0] $end
$var reg 8 4 pattern [7:0] $end
$var reg 1 $ wr_en $end
$upscope $end
$scope module fifo $end
$var wire 1 " clk $end
$var wire 8 5 din [7:0] $end
$var wire 1 & full $end
$var wire 1 % rd_en $end
$var wire 1 # rst $end
$var wire 1 $ wr_en $end
$var wire 1 ' empty $end
$var parameter 32 6 Addr_Width $end
$var parameter 32 7 Depth $end
$var parameter 32 8 Width $end
$var reg 8 9 dout [7:0] $end
$var reg 4 : rd_ptr [3:0] $end
$var reg 4 ; wr_ptr [3:0] $end
$var integer 32 < i [31:0] $end
$upscope $end
$upscope $end
$upscope $end
$enddefinitions $end
$comment Show the parameter values. $end
$dumpall
b1000 8
b1000 7
b11 6
b1000 1
b1000 -
b1000 +
$end
#0
$dumpvars
bx <
bx ;
bx :
bx 9
bx 5
b10100101 4
bx 3
bx 2
x0
b10100101 /
bx .
bx ,
bx *
bx )
bx (
x'
x&
x%
x$
1#
0"
0!
$end
#6
0&
0$
b0 *
b0 3
b0 5
b0 2
1'
b0 ;
b0 (
b0 ,
b0 9
b0 :
b1000 <
1"
#10
0%
b0 )
b0 .
00
1!
#12
0"
#18
b1000 <
1"
#20
0!
0#
#24
0"
#30
b1 2
1$
b10100101 *
b10100101 3
b10100101 5
1"
1!
#36
0"
#40
0!
#42
0'
b1 ;
b10 2
b10100100 *
b10100100 3
b10100100 5
1"
#48
0"
#50
1!
#54
b11 2
b10100111 *
b10100111 3
b10100111 5
b10 ;
1"
#60
0"
0!
#66
b11 ;
b100 2
b10100110 *
b10100110 3
b10100110 5
1"
#70
1!
#72
0"
#78
b101 2
b10100001 *
b10100001 3
b10100001 5
b100 ;
1"
#80
0!
#84
0"
#90
b101 ;
b110 2
b10100000 *
b10100000 3
b10100000 5
1"
1!
#96
0"
#100
0!
#102
b111 2
b10100011 *
b10100011 3
b10100011 5
b110 ;
1"
#108
0"
#110
1!
#114
b111 ;
b1000 2
b10100010 *
b10100010 3
b10100010 5
1"
#120
0"
0!
#126
1&
b1001 2
b10101101 *
b10101101 3
b10101101 5
b1000 ;
1"
#130
10
1!
#132
0"
#138
0$
1"
#140
0!
#144
0"
#150
b10100101 )
b10100101 .
1%
1"
1!
#156
0"
#160
0!
#162
0&
b1 :
b10100101 (
b10100101 ,
b10100101 9
1"
#168
0"
#170
b0 )
b0 .
1!
#174
b1010 2
1$
b10101100 *
b10101100 3
b10101100 5
b10 :
b10100100 (
b10100100 ,
b10100100 9
1"
#180
0"
0!
#186
b11 :
b10100111 (
b10100111 ,
b10100111 9
b1001 ;
b1011 2
b10101111 *
b10101111 3
b10101111 5
1"
#190
b10 )
b10 .
1!
#192
0"
#198
b1100 2
b10101110 *
b10101110 3
b10101110 5
b1010 ;
b100 :
b10100110 (
b10100110 ,
b10100110 9
1"
#200
0!
#204
0"
#210
b101 :
b10100001 (
b10100001 ,
b10100001 9
b1011 ;
b1101 2
b10101001 *
b10101001 3
b10101001 5
b11 )
b11 .
1"
1!
